KTLib/KTLib.py
KTLib/__init__.py
KT_Lib/KT_Lib.py
KT_Lib/__init__.py
Tello/Tello.py
Tello/__init__.py
KT_Lib-1.0.2.dist-info/LICENSE
KT_Lib-1.0.2.dist-info/METADATA
KT_Lib-1.0.2.dist-info/WHEEL
KT_Lib-1.0.2.dist-info/top_level.txt
KT_Lib-1.0.2.dist-info/RECORD
